Metadata-Version: 2.1
Name: odoo14-addon-l10n_it_account
Version: 14.0.1.4.5
Summary: Modulo base usato come dipendenza di altri moduli contabili
Home-page: https://github.com/OCA/l10n-italy
Author: Agile Business Group, Abstract, Odoo Community Association (OCA)
Author-email: support@odoo-community.org
License: AGPL-3
Classifier: Programming Language :: Python
Classifier: Framework :: Odoo
Classifier: Framework :: Odoo :: 14.0
Classifier: License :: OSI Approved :: GNU Affero General Public License v3
Classifier: Development Status :: 5 - Production/Stable
Requires-Python: >=3.6
Requires-Dist: odoo14-addon-account-fiscal-year
Requires-Dist: odoo14-addon-account-tax-balance
Requires-Dist: odoo14-addon-date-range
Requires-Dist: odoo<14.1dev,>=14.0a
Requires-Dist: xmlschema>=1.7.0
